hyperbrowser/__init__.py
hyperbrowser/client/async_client.py
hyperbrowser/client/base.py
hyperbrowser/client/managers/async_manager/agents/__init__.py
hyperbrowser/client/managers/async_manager/agents/browser_use.py
hyperbrowser/client/managers/async_manager/agents/claude_computer_use.py
hyperbrowser/client/managers/async_manager/agents/cua.py
hyperbrowser/client/managers/async_manager/agents/gemini_computer_use.py
hyperbrowser/client/managers/async_manager/agents/hyper_agent.py
hyperbrowser/client/managers/async_manager/computer_action.py
hyperbrowser/client/managers/async_manager/crawl.py
hyperbrowser/client/managers/async_manager/extension.py
hyperbrowser/client/managers/async_manager/extract.py
hyperbrowser/client/managers/async_manager/profile.py
hyperbrowser/client/managers/async_manager/scrape.py
hyperbrowser/client/managers/async_manager/session.py
hyperbrowser/client/managers/async_manager/team.py
hyperbrowser/client/managers/async_manager/web/__init__.py
hyperbrowser/client/managers/async_manager/web/batch_fetch.py
hyperbrowser/client/managers/sync_manager/agents/__init__.py
hyperbrowser/client/managers/sync_manager/agents/browser_use.py
hyperbrowser/client/managers/sync_manager/agents/claude_computer_use.py
hyperbrowser/client/managers/sync_manager/agents/cua.py
hyperbrowser/client/managers/sync_manager/agents/gemini_computer_use.py
hyperbrowser/client/managers/sync_manager/agents/hyper_agent.py
hyperbrowser/client/managers/sync_manager/computer_action.py
hyperbrowser/client/managers/sync_manager/crawl.py
hyperbrowser/client/managers/sync_manager/extension.py
hyperbrowser/client/managers/sync_manager/extract.py
hyperbrowser/client/managers/sync_manager/profile.py
hyperbrowser/client/managers/sync_manager/scrape.py
hyperbrowser/client/managers/sync_manager/session.py
hyperbrowser/client/managers/sync_manager/team.py
hyperbrowser/client/managers/sync_manager/web/__init__.py
hyperbrowser/client/managers/sync_manager/web/batch_fetch.py
hyperbrowser-0.82.2.dist-info/METADATA
hyperbrowser-0.82.2.dist-info/WHEEL
hyperbrowser-0.82.2.dist-info/licenses/LICENSE
hyperbrowser-0.82.2.dist-info/RECORD
