Metadata-Version: 2.4
Name: hyperbrowser
Version: 0.82.2
Summary: Python SDK for hyperbrowser
License: MIT
License-File: LICENSE
Author: Nikhil Shahi
Author-email: nshahi1998@gmail.com
Requires-Python: >=3.8,<4.0
Classifier: License :: OSI Approved :: MIT License
Classifier: Programming Language :: Python :: 3
Classifier: Programming Language :: Python :: 3.8
Classifier: Programming Language :: Python :: 3.9
Classifier: Programming Language :: Python :: 3.10
Classifier: Programming Language :: Python :: 3.11
Classifier: Programming Language :: Python :: 3.12
Classifier: Programming Language :: Python :: 3.13
Classifier: Programming Language :: Python :: 3.14
Requires-Dist: httpx (>=0.23.0,<1)
Requires-Dist: jsonref (>=1.1.0)
Requires-Dist: pydantic (>=2.0,<3)
Project-URL: Homepage, https://github.com/hyperbrowserai/python-sdk
Project-URL: Repository, https://github.com/hyperbrowserai/python-sdk
